{"frames":{"sketchHome-sketchHome1":{"frame":{"x":1,"y":1,"w":241,"h":220},"sourceSize":{"w":241,"h":220}},"sketchBattery-sketchBattery1":{"frame":{"x":244,"y":1,"w":207,"h":114},"sourceSize":{"w":207,"h":114}},"sketchTurbineCone1":{"frame":{"x":244,"y":117,"w":37,"h":25},"sourceSize":{"w":37,"h":25}},"sketchDot11":{"frame":{"x":244,"y":144,"w":25,"h":25},"sourceSize":{"w":25,"h":25}},"sketchDot21":{"frame":{"x":244,"y":171,"w":24,"h":26},"sourceSize":{"w":24,"h":26}},"sketchDot31":{"frame":{"x":283,"y":117,"w":24,"h":24},"sourceSize":{"w":24,"h":24}},"sketchTurbineBlades1":{"frame":{"x":453,"y":1,"w":178,"h":158},"sourceSize":{"w":178,"h":158}},"sketchTurbineTower1":{"frame":{"x":1,"y":223,"w":75,"h":245},"sourceSize":{"w":75,"h":245}},"grid-bg-compressed_2":{"frame":{"x":78,"y":223,"w":1536,"h":768},"sourceSize":{"w":1536,"h":768}}},"meta":{"app":"PixiAnimate","scale":1,"image":"Transition_atlas_1.png","size":{"w":2048,"h":2048}}}