{
	"groups":[
	{
		"keys":"img_bgpause,img_bgstart,img_boa3,img_boya1,img_boybody,img_btnjixu,img_btnmore,img_btn_return,img_gamebg,img_girlbo1,img_girlbody,img_girlr1,img_guang1,img_helpbg,img_hou,img_loses,img_mia1,img_mian,img_monkybody,img_monkyw1,img_more,img_next,img_normal,img_nvsheng,img_play,img_ren1,img_winshang,img_xia,img_yanlei1,img_yanlei2,img_yanlei3,img_yanlei4,img_zheng1,img_zheng2,game_swf,img_a1,img_a2,img_anniu,img_app,img_asd2,img_bar,img_facebook,img_girlyanzhu,img_girlyanzhu2,img_google,img_google_plus,img_gq1,img_houyan1,img_hye1,img_jias1,img_jija1,img_mask,img_mi12,img_nanhaizui,img_nany3,img_nany4,img_nanyang2,img_nanyw1,img_nan_bg,img_ncbiyan,img_nose,img_qq,img_qw1,img_qw2,img_s1,img_score,img_sda1,img_shang,img_shui2,img_shui3,img_tool1,img_tool2,img_tool3,img_tool4,img_tool5,img_tool6,img_twitter,img_weibo,img_yanhou",
		"name":"preload"
	}],
	"resources":[
	{
		"name":"img_bgpause",
		"type":"image",
		"url":"assets/game/big_images/img_bgpause.png"
	},
	{
		"name":"img_bgstart",
		"type":"image",
		"url":"assets/game/big_images/img_bgstart.png"
	},
	{
		"name":"img_boa3",
		"type":"image",
		"url":"assets/game/big_images/img_boa3.png"
	},
	{
		"name":"img_boya1",
		"type":"image",
		"url":"assets/game/big_images/img_boya1.png"
	},
	{
		"name":"img_boybody",
		"type":"image",
		"url":"assets/game/big_images/img_boybody.png"
	},
	{
		"name":"img_btnjixu",
		"type":"image",
		"url":"assets/game/big_images/img_btnjixu.png"
	},
	{
		"name":"img_btnmore",
		"type":"image",
		"url":"assets/game/big_images/img_btnmore.png"
	},
	{
		"name":"img_btn_return",
		"type":"image",
		"url":"assets/game/big_images/img_btn_return.png"
	},
	{
		"name":"img_gamebg",
		"type":"image",
		"url":"assets/game/big_images/img_gamebg.png"
	},
	{
		"name":"img_girlbo1",
		"type":"image",
		"url":"assets/game/big_images/img_girlbo1.png"
	},
	{
		"name":"img_girlbody",
		"type":"image",
		"url":"assets/game/big_images/img_girlbody.png"
	},
	{
		"name":"img_girlr1",
		"type":"image",
		"url":"assets/game/big_images/img_girlr1.png"
	},
	{
		"name":"img_guang1",
		"type":"image",
		"url":"assets/game/big_images/img_guang1.png"
	},
	{
		"name":"img_helpbg",
		"type":"image",
		"url":"assets/game/big_images/img_helpbg.png"
	},
	{
		"name":"img_hou",
		"type":"image",
		"url":"assets/game/big_images/img_hou.png"
	},
	{
		"name":"img_loses",
		"type":"image",
		"url":"assets/game/big_images/img_loses.png"
	},
	{
		"name":"img_mia1",
		"type":"image",
		"url":"assets/game/big_images/img_mia1.png"
	},
	{
		"name":"img_mian",
		"type":"image",
		"url":"assets/game/big_images/img_mian.png"
	},
	{
		"name":"img_monkybody",
		"type":"image",
		"url":"assets/game/big_images/img_monkybody.png"
	},
	{
		"name":"img_monkyw1",
		"type":"image",
		"url":"assets/game/big_images/img_monkyw1.png"
	},
	{
		"name":"img_more",
		"type":"image",
		"url":"assets/game/big_images/img_more.png"
	},
	{
		"name":"img_next",
		"type":"image",
		"url":"assets/game/big_images/img_next.png"
	},
	{
		"name":"img_normal",
		"type":"image",
		"url":"assets/game/big_images/img_normal.png"
	},
	{
		"name":"img_nvsheng",
		"type":"image",
		"url":"assets/game/big_images/img_nvsheng.png"
	},
	{
		"name":"img_play",
		"type":"image",
		"url":"assets/game/big_images/img_play.png"
	},
	{
		"name":"img_ren1",
		"type":"image",
		"url":"assets/game/big_images/img_ren1.png"
	},
	{
		"name":"img_winshang",
		"type":"image",
		"url":"assets/game/big_images/img_winshang.png"
	},
	{
		"name":"img_xia",
		"type":"image",
		"url":"assets/game/big_images/img_xia.png"
	},
	{
		"name":"img_yanlei1",
		"type":"image",
		"url":"assets/game/big_images/img_yanlei1.png"
	},
	{
		"name":"img_yanlei2",
		"type":"image",
		"url":"assets/game/big_images/img_yanlei2.png"
	},
	{
		"name":"img_yanlei3",
		"type":"image",
		"url":"assets/game/big_images/img_yanlei3.png"
	},
	{
		"name":"img_yanlei4",
		"type":"image",
		"url":"assets/game/big_images/img_yanlei4.png"
	},
	{
		"name":"img_zheng1",
		"type":"image",
		"url":"assets/game/big_images/img_zheng1.png"
	},
	{
		"name":"img_zheng2",
		"type":"image",
		"url":"assets/game/big_images/img_zheng2.png"
	},
	{
		"name":"game_swf",
		"type":"json",
		"url":"assets/game/game_swf.json"
	},
	{
		"name":"img_a1",
		"type":"image",
		"url":"assets/game/images/img_a1.png"
	},
	{
		"name":"img_a2",
		"type":"image",
		"url":"assets/game/images/img_a2.png"
	},
	{
		"name":"img_anniu",
		"type":"image",
		"url":"assets/game/images/img_anniu.png"
	},
	{
		"name":"img_app",
		"type":"image",
		"url":"assets/game/images/img_app.png"
	},
	{
		"name":"img_asd2",
		"type":"image",
		"url":"assets/game/images/img_asd2.png"
	},
	{
		"name":"img_bar",
		"type":"image",
		"url":"assets/game/images/img_bar.png"
	},
	{
		"name":"img_facebook",
		"type":"image",
		"url":"assets/game/images/img_facebook.png"
	},
	{
		"name":"img_girlyanzhu",
		"type":"image",
		"url":"assets/game/images/img_girlyanzhu.png"
	},
	{
		"name":"img_girlyanzhu2",
		"type":"image",
		"url":"assets/game/images/img_girlyanzhu2.png"
	},
	{
		"name":"img_google",
		"type":"image",
		"url":"assets/game/images/img_google.png"
	},
	{
		"name":"img_google_plus",
		"type":"image",
		"url":"assets/game/images/img_google_plus.png"
	},
	{
		"name":"img_gq1",
		"type":"image",
		"url":"assets/game/images/img_gq1.png"
	},
	{
		"name":"img_houyan1",
		"type":"image",
		"url":"assets/game/images/img_houyan1.png"
	},
	{
		"name":"img_hye1",
		"type":"image",
		"url":"assets/game/images/img_hye1.png"
	},
	{
		"name":"img_jias1",
		"type":"image",
		"url":"assets/game/images/img_jias1.png"
	},
	{
		"name":"img_jija1",
		"type":"image",
		"url":"assets/game/images/img_jija1.png"
	},
	{
		"name":"img_mask",
		"type":"image",
		"url":"assets/game/images/img_mask.png"
	},
	{
		"name":"img_mi12",
		"type":"image",
		"url":"assets/game/images/img_mi12.png"
	},
	{
		"name":"img_nanhaizui",
		"type":"image",
		"url":"assets/game/images/img_nanhaizui.png"
	},
	{
		"name":"img_nany3",
		"type":"image",
		"url":"assets/game/images/img_nany3.png"
	},
	{
		"name":"img_nany4",
		"type":"image",
		"url":"assets/game/images/img_nany4.png"
	},
	{
		"name":"img_nanyang2",
		"type":"image",
		"url":"assets/game/images/img_nanyang2.png"
	},
	{
		"name":"img_nanyw1",
		"type":"image",
		"url":"assets/game/images/img_nanyw1.png"
	},
	{
		"name":"img_nan_bg",
		"type":"image",
		"url":"assets/game/images/img_nan_bg.png"
	},
	{
		"name":"img_ncbiyan",
		"type":"image",
		"url":"assets/game/images/img_ncbiyan.png"
	},
	{
		"name":"img_nose",
		"type":"image",
		"url":"assets/game/images/img_nose.png"
	},
	{
		"name":"img_qq",
		"type":"image",
		"url":"assets/game/images/img_qq.png"
	},
	{
		"name":"img_qw1",
		"type":"image",
		"url":"assets/game/images/img_qw1.png"
	},
	{
		"name":"img_qw2",
		"type":"image",
		"url":"assets/game/images/img_qw2.png"
	},
	{
		"name":"img_s1",
		"type":"image",
		"url":"assets/game/images/img_s1.png"
	},
	{
		"name":"img_score",
		"type":"image",
		"url":"assets/game/images/img_score.png"
	},
	{
		"name":"img_sda1",
		"type":"image",
		"url":"assets/game/images/img_sda1.png"
	},
	{
		"name":"img_shang",
		"type":"image",
		"url":"assets/game/images/img_shang.png"
	},
	{
		"name":"img_shui2",
		"type":"image",
		"url":"assets/game/images/img_shui2.png"
	},
	{
		"name":"img_shui3",
		"type":"image",
		"url":"assets/game/images/img_shui3.png"
	},
	{
		"name":"img_tool1",
		"type":"image",
		"url":"assets/game/images/img_tool1.png"
	},
	{
		"name":"img_tool2",
		"type":"image",
		"url":"assets/game/images/img_tool2.png"
	},
	{
		"name":"img_tool3",
		"type":"image",
		"url":"assets/game/images/img_tool3.png"
	},
	{
		"name":"img_tool4",
		"type":"image",
		"url":"assets/game/images/img_tool4.png"
	},
	{
		"name":"img_tool5",
		"type":"image",
		"url":"assets/game/images/img_tool5.png"
	},
	{
		"name":"img_tool6",
		"type":"image",
		"url":"assets/game/images/img_tool6.png"
	},
	{
		"name":"img_twitter",
		"type":"image",
		"url":"assets/game/images/img_twitter.png"
	},
	{
		"name":"img_weibo",
		"type":"image",
		"url":"assets/game/images/img_weibo.png"
	},
	{
		"name":"img_yanhou",
		"type":"image",
		"url":"assets/game/images/img_yanhou.png"
	}]
}